Metastability/metastability.v
`timescale 1ns / 1ps
//////////////////////////////////////////////////////////////////////////////////
// Company: 
// Engineer: 
// 
// Create Date: 06/23/2025 06:21:48 PM
// Design Name: 
// Module Name: metastability
// Project Name: 
// Target Devices: 
// Tool Versions: 
// Description: 
// 
// Dependencies: 
// 
// Revision:
// Revision 0.01 - File Created
// Additional Comments:
// 
//////////////////////////////////////////////////////////////////////////////////


module metastability(
    input wire clk,
    input wire async_in,
    output reg sync_out
    );
    
    reg sync_ff1;

    always @(posedge clk) begin
        sync_ff1  <= async_in; // first stage may become metastable
        sync_out  <= sync_ff1; // second stage likely resolves it
    end
    
endmodule

Metastability/metastability_tb.v
`timescale 1ns / 1ps
//////////////////////////////////////////////////////////////////////////////////
// Company: 
// Engineer: 
// 
// Create Date: 06/23/2025 06:24:51 PM
// Design Name: 
// Module Name: metastability_tb
// Project Name: 
// Target Devices: 
// Tool Versions: 
// Description: 
// 
// Dependencies: 
// 
// Revision:
// Revision 0.01 - File Created
// Additional Comments:
// 
//////////////////////////////////////////////////////////////////////////////////


module metastability_tb();

    reg clk;
    reg async_in;
    wire sync_out;

    // Instantiate the DUT
    metastability uut (
        .clk(clk),
        .async_in(async_in),
        .sync_out(sync_out)
    );
    
    // Clock generator (period = 10ns)
    initial clk = 0;
    always #5 clk = ~clk;

    // Stimulus
    initial begin
        $dumpfile("metastability.vcd");
        $dumpvars(0, metastability_tb);

        async_in = 0;

        // Change async_in in middle of clock period to induce potential metastability
        #12 async_in = 1;
        #7  async_in = 0;
        #3  async_in = 1;
        #9  async_in = 0;

        // Hold steady to allow stabilizing
        #50;

        $finish;
    end
    
endmodule

Metastability/metastability.vcd
$date
	Tue Jun 24 20:49:31 2025
$end
$version
	Icarus Verilog
$end
$timescale
	1ps
$end
$scope module metastability_tb $end
$var wire 1 ! sync_out $end
$var reg 1 " async_in $end
$var reg 1 # clk $end
$scope module uut $end
$var wire 1 $ async_in $end
$var wire 1 % clk $end
$var reg 1 & sync_ff1 $end
$var reg 1 ' sync_out $end
$upscope $end
$upscope $end
$enddefinitions $end
#0
$dumpvars
x'
x&
0%
0$
0#
0"
x!
$end
#5000
0&
1#
1%
#10000
0#
0%
#12000
1"
1$
#15000
0'
0!
1&
1#
1%
#19000
0"
0$
#20000
0#
0%
#22000
1"
1$
#25000
1'
1!
1#
1%
#30000
0#
0%
#31000
0"
0$
#35000
0&
1#
1%
#40000
0#
0%
#45000
0'
0!
1#
1%
